boosty_downloader/__init__.py
boosty_downloader/main.py
boosty_downloader/src/__init__.py
boosty_downloader/src/application/__init__.py
boosty_downloader/src/application/di/__init__.py
boosty_downloader/src/application/di/app_environment.py
boosty_downloader/src/application/di/download_context.py
boosty_downloader/src/application/exceptions/__init__.py
boosty_downloader/src/application/exceptions/application_errors.py
boosty_downloader/src/application/filtering.py
boosty_downloader/src/application/mappers/__init__.py
boosty_downloader/src/application/mappers/audio.py
boosty_downloader/src/application/mappers/external_video.py
boosty_downloader/src/application/mappers/file.py
boosty_downloader/src/application/mappers/html_converter.py
boosty_downloader/src/application/mappers/image.py
boosty_downloader/src/application/mappers/link_header_text.py
boosty_downloader/src/application/mappers/list.py
boosty_downloader/src/application/mappers/ok_boosty_video.py
boosty_downloader/src/application/mappers/post_mapper.py
boosty_downloader/src/application/ok_video_ranking.py
boosty_downloader/src/application/use_cases/__init__.py
boosty_downloader/src/application/use_cases/check_total_posts.py
boosty_downloader/src/application/use_cases/download_all_posts.py
boosty_downloader/src/application/use_cases/download_single_post.py
boosty_downloader/src/application/use_cases/download_specific_post.py
boosty_downloader/src/cli/__init__.py
boosty_downloader/src/cli/cli_options.py
boosty_downloader/src/cli/console_progress_reporter.py
boosty_downloader/src/cli/help_panels.py
boosty_downloader/src/domain/__init__.py
boosty_downloader/src/domain/post.py
boosty_downloader/src/domain/post_data_chunks.py
boosty_downloader/src/infrastructure/__init__.py
boosty_downloader/src/infrastructure/boosty_api/__init__.py
boosty_downloader/src/infrastructure/boosty_api/core/__init__.py
boosty_downloader/src/infrastructure/boosty_api/core/client.py
boosty_downloader-2.1.0.dist-info/METADATA
boosty_downloader-2.1.0.dist-info/WHEEL
boosty_downloader-2.1.0.dist-info/entry_points.txt
boosty_downloader-2.1.0.dist-info/licenses/LICENSE
boosty_downloader-2.1.0.dist-info/RECORD
