Metadata-Version: 2.4
Name: boosty-downloader
Version: 2.1.0
Summary: Download any type of content from boosty.to
License-File: LICENSE
Author: Roman Berezkin
Author-email: Glitchy-Sheep@users.noreply.github.com
Requires-Python: >=3.10,<4
Classifier: Programming Language :: Python :: 3
Classifier: Programming Language :: Python :: 3.10
Classifier: Programming Language :: Python :: 3.11
Classifier: Programming Language :: Python :: 3.12
Classifier: Programming Language :: Python :: 3.13
Classifier: Programming Language :: Python :: 3.14
Requires-Dist: aiofiles (>=24.1.0,<25.0.0)
Requires-Dist: aiohttp (>=3.11.12,<4.0.0)
Requires-Dist: aiohttp-retry (>=2.9.1,<3.0.0)
Requires-Dist: aiolimiter (>=1.2.1,<2.0.0)
Requires-Dist: asyncio (>=3.4.3,<4.0.0)
Requires-Dist: jinja2 (>=3.1.5,<4.0.0)
Requires-Dist: packaging (>=25.0,<26.0)
Requires-Dist: pydantic (>=2.10.6,<3.0.0)
Requires-Dist: pydantic-settings[yaml] (>=2.7.1,<3.0.0)
Requires-Dist: rich (>=14.0.0,<14.1.0)
Requires-Dist: sqlalchemy (>=2.0.42,<3.0.0)
Requires-Dist: typer (>=0.16.0,<0.17.0)
Requires-Dist: yarl (>=1.18.3,<2.0.0)
Requires-Dist: yt-dlp (>=2025.1.26,<2026.0.0)
